domina.py
domina_util.py
domina-0.1.0a3.dist-info/LICENSE
domina-0.1.0a3.dist-info/METADATA
domina-0.1.0a3.dist-info/WHEEL
domina-0.1.0a3.dist-info/entry_points.txt
domina-0.1.0a3.dist-info/top_level.txt
domina-0.1.0a3.dist-info/RECORD
