Metadata-Version: 2.1
Name: domina
Version: 0.1.0a3
Summary: Game AI script framework for MMORTS screeps.com
Home-page: https://gitlab.com/screeps-domina/domina
Author: hexanona
Author-email: hexanona+domina@mailbox.org
License: GPLv3
Platform: UNKNOWN
Classifier: Topic :: Games/Entertainment :: Real Time Strategy
Classifier: Topic :: Software Development :: Version Control
Classifier: Intended Audience :: Developers
Classifier: Environment :: Console
Classifier: Natural Language :: English
Classifier: License :: OSI Approved :: GNU General Public License v3 (GPLv3)
Classifier: Operating System :: POSIX :: Linux
Classifier: Programming Language :: Python :: 3.7
Classifier: Programming Language :: JavaScript
Classifier: Development Status :: 1 - Planning
Requires-Python: >=3.7
Requires-Dist: Click
